cli.py
fastapi_template/__init__.py
fastapi_template/main.py
fastapi_cli_starter-0.2.dist-info/METADATA
fastapi_cli_starter-0.2.dist-info/WHEEL
fastapi_cli_starter-0.2.dist-info/entry_points.txt
fastapi_cli_starter-0.2.dist-info/top_level.txt
fastapi_cli_starter-0.2.dist-info/RECORD
